django_cached_field/__init__.py
django_cached_field/constants.py
django_cached_field/tasks.py
django_cached_field-1.3.1.dist-info/AUTHORS
django_cached_field-1.3.1.dist-info/LICENSE
django_cached_field-1.3.1.dist-info/METADATA
django_cached_field-1.3.1.dist-info/WHEEL
django_cached_field-1.3.1.dist-info/entry_points.txt
django_cached_field-1.3.1.dist-info/top_level.txt
django_cached_field-1.3.1.dist-info/RECORD
