Metadata-Version: 2.1
Name: django-cached-field
Version: 1.3.1
Summary: Celery-deferred, cached fields on Django ORM for expensive-to-calculate attributes
Home-page: https://github.com/outofculture/django-cached-field
Author: Martin Chase
Author-email: outofculture@gmail.com
License: BSD
Keywords: django caching
Platform: UNKNOWN
Requires-Dist: django (>=1.9)
Requires-Dist: celery (>=3.0)
